AUTHORS
COPYING
LICENSE
MANIFEST.in
NEWS
NEWS.rst
README
pyproject.toml
setup.py
examples/drop_privileges.py
examples/joystick.py
examples/keyboard.py
examples/mouse.py
libsuinput/src/libudev.h
libsuinput/src/suinput.c
libsuinput/src/suinput.h
python_uinput2.egg-info/PKG-INFO
python_uinput2.egg-info/SOURCES.txt
python_uinput2.egg-info/dependency_links.txt
python_uinput2.egg-info/top_level.txt
src/__init__.py
src/ev.py
tests/test_uinput.py
udev-rules/40-uinput.rules