Metadata-Version: 2.1
Name: python-uinput2
Version: 2.0.0
Summary: Pythonic API to Linux uinput kernel module.
Home-page: https://github.com/pyinput/python-uinput2
Author: Tuomas Räsänen
Author-email: tuomasjjrasanen@tjjr.fi
License: GPLv3+
Project-URL: Homepage, https://github.com/pyinput/python-uinput2
Platform: Linux
Classifier: Development Status :: 5 - Production/Stable
Classifier: Intended Audience :: Developers
Classifier: License :: OSI Approved :: GNU General Public License (GPL)
Classifier: Operating System :: POSIX :: Linux
Classifier: Topic :: System :: Operating System Kernels :: Linux
Classifier: Programming Language :: Python
Classifier: Programming Language :: Python :: 2
Classifier: Programming Language :: Python :: 2.7
Classifier: Programming Language :: Python :: 3
Classifier: Programming Language :: Python :: 3.12
Requires-Python: >=2.7
License-File: LICENSE
License-File: COPYING
License-File: AUTHORS
